test_hatch/__about__.py
test_hatch/__init__.py
test_hatch/__main__.py
test_hatch-0.0.2.dist-info/METADATA
test_hatch-0.0.2.dist-info/WHEEL
test_hatch-0.0.2.dist-info/licenses/LICENSE.txt
test_hatch-0.0.2.dist-info/RECORD
