Metadata-Version: 2.4
Name: test-hatch
Version: 0.0.2
Project-URL: Documentation, https://github.com/Naman Goyal/test-hatch#readme
Project-URL: Issues, https://github.com/Naman Goyal/test-hatch/issues
Project-URL: Source, https://github.com/Naman Goyal/test-hatch
Author-email: Naman Goyal <naman.goyal@zypp.app>
License-Expression: MIT
License-File: LICENSE.txt
Classifier: Development Status :: 4 - Beta
Classifier: Programming Language :: Python
Classifier: Programming Language :: Python :: 3.8
Classifier: Programming Language :: Python :: 3.9
Classifier: Programming Language :: Python :: 3.10
Classifier: Programming Language :: Python :: 3.11
Classifier: Programming Language :: Python :: 3.12
Classifier: Programming Language :: Python :: Implementation :: CPython
Classifier: Programming Language :: Python :: Implementation :: PyPy
Requires-Python: >=3.8
Requires-Dist: pandas
